{
  "files": {
    "summary": "/Users/pechen/AI/QuantTrading/strategies/qmt四季发财v3/results/backtest-export-2026-06-19-r3/raw/qmt四季发财v3-r3-收益概述-2026-06-19.csv",
    "transaction": "/Users/pechen/AI/QuantTrading/strategies/qmt四季发财v3/results/backtest-export-2026-06-19-r3/extracted/transaction/transaction.csv",
    "position": "/Users/pechen/AI/QuantTrading/strategies/qmt四季发财v3/results/backtest-export-2026-06-19-r3/extracted/position/position.csv",
    "log": "/Users/pechen/AI/QuantTrading/strategies/qmt四季发财v3/results/backtest-export-2026-06-19-r3/extracted/log/log.txt"
  },
  "encodings": {
    "summary": "gb18030",
    "transaction": "gb18030",
    "position": "gb18030",
    "log": "gb18030"
  },
  "rows": {
    "summary": 1455,
    "transaction": 876,
    "position": 2926,
    "log_lines": 19867,
    "jq_audit": 9503,
    "jq_audit_parse_errors": 9503,
    "jq_audit_parse_errors_html_unescaped": 0
  },
  "date_range": [
    "2020-01-02 16:00:00",
    "2025-12-31 16:00:00"
  ],
  "performance": {
    "final_equity": 26388500.0,
    "strategy_total_return": 25.3885,
    "benchmark_total_return": 1.9828000000000001,
    "annualized_return": 0.7260950721190835,
    "benchmark_annualized_return": 0.1999363320596652,
    "annualized_vol": 0.2931793447346672,
    "sharpe_rf0": 2.0805581157306676,
    "max_drawdown": -0.2002634082095559,
    "max_drawdown_date": "2021-09-01 16:00:00",
    "best_day": [
      "2024-10-08 16:00:00",
      0.10075098294874496
    ],
    "worst_day": [
      "2025-01-27 16:00:00",
      -0.08774856048849122
    ]
  },
  "yearly": {
    "2020": {
      "strategy_return": 0.7907,
      "benchmark_return": 0.3702000000000001,
      "end_equity": 1790700.0,
      "days": 243
    },
    "2021": {
      "strategy_return": 0.2658178366002124,
      "benchmark_return": 0.2260253977521529,
      "end_equity": 2266700.0,
      "days": 243
    },
    "2022": {
      "strategy_return": 0.8329730445140511,
      "benchmark_return": -0.2548365974165129,
      "end_equity": 4154800.0,
      "days": 242
    },
    "2023": {
      "strategy_return": 0.38488013863483195,
      "benchmark_return": 0.5178942323054803,
      "end_equity": 5753900.0,
      "days": 242
    },
    "2024": {
      "strategy_return": 1.1162689653973827,
      "benchmark_return": 0.3429819483185095,
      "end_equity": 12176800.0,
      "days": 242
    },
    "2025": {
      "strategy_return": 1.1671128703764535,
      "benchmark_return": 0.16890038404263663,
      "end_equity": 26388500.0,
      "days": 243
    }
  },
  "transactions": {
    "buy_count": 439,
    "sell_count": 437,
    "total_buy_amount": 2877942033.1400003,
    "total_sell_amount": 2878054176.5759997,
    "total_fee": 1117134.3200000003,
    "sell_rows": 437,
    "sell_win_rate": 0.5308924485125858,
    "sell_realized_pnl": 25289116.25
  },
  "log": {
    "first_line": "2020-01-01 00:00:00 - INFO  - 策略2优化版初始化完成 - 包含完整实盘交易设置和短期动量过滤",
    "last_line": "2025-12-31 14:29:00 - INFO  - JQ_AUDIT|{&quot;audit_peak_value&quot;: 26996783.452016816, &quot;audit_start_value&quot;: 1000000.0, &quot;available_cash&quot;: -4990.947983181176, &quot;benchmark&quot;: {&quot;benchmark_drawdown_from_peak&quot;: -0.650697503671072, &quot;benchmark_peak_price&quot;: 5.448, &quot;benchmark_price&quot;: 1.903, &quot;benchmark_return&quot;: -0.4040087691825869, &quot;benchmark_security&quot;: &quot;513100.XSHG&quot;, &quot;benchmark_start_price&quot;: 3.193}, &quot;cash_ratio&quot;: -0.00018941808152347168, &quot;cumulative_return&quot;: 25.348846652016817, &quot;drawdown_from_peak&quot;: -0.024000518474788568, &quot;dt&quot;: &quot;2025-12-31 14:29:00&quot;, &quot;event&quot;: &quot;after_rebalance&quot;, &quot;excess_return_vs_benchmark&quot;: 25.752855421199403, &quot;exposure&quot;: 1.0001894180815236, &quot;position_count&quot;: 1, &quot;position_value&quot;: 26353837.6, &quot;positions&quot;: [{&quot;amount&quot;: 13223200, &quot;avg_cost&quot;: 1.9039999999999997, &quot;closeable_amount&quot;: 13223200, &quot;name&quot;: &quot;\\u6709\\u8272ETF\\u5927\\u6210&quot;, &quot;pnl_pct&quot;: 0.046743697478991875, &quot;price&quot;: 1.993, &quot;security&quot;: &quot;159980.XSHE&quot;, &quot;value&quot;: 26353837.6}], &quot;rule&quot;: &quot;ETF\\u8f6e\\u52a8\\u8c03\\u4ed3\\u540e\\u7ec4\\u5408\\u72b6\\u6001\\uff0c\\u7528\\u4e8e\\u8bc4\\u4f30\\u6536\\u76ca\\u3001\\u56de\\u64a4\\u3001\\u73b0\\u91d1\\u5360\\u6bd4\\u548c\\u6301\\u4ed3\\u66b4\\u9732&quot;, &quot;selection_mode&quot;: &quot;normal&quot;, &quot;selection_reason&quot;: &quot;top_score_above_min_score_threshold&quot;, &quot;target_etfs&quot;: [&quot;159980.XSHE&quot;], &quot;total_value&quot;: 26348846.65201682}",
    "limit_line": false,
    "event_counts": {},
    "strategy_metadata": [],
    "rsi_info_error_lines": 0,
    "order_fail_lines": 3,
    "insufficient_cash_order_fail_lines": 3,
    "event_counts_html_unescaped": {
      "strategy_metadata": 1,
      "daily_position_check": 1455,
      "rebalance_universe_summary": 1455,
      "target_selection": 1455,
      "rebalance_plan": 1455,
      "position_adjustment_needed": 443,
      "order_decision": 884,
      "order_result": 879,
      "after_rebalance": 1455,
      "risk_event": 21
    },
    "strategy_metadata_html_unescaped": [
      {
        "audit_log_policy": "summary_only",
        "audit_reject_sample_limit": 8,
        "audit_top_candidate_count": 3,
        "benchmark": "513100.XSHG",
        "defensive_etf": "511880.XSHG",
        "description": "ETF轮动策略：长期动量稳定性得分、短期动量过滤、RSI过滤、ATR动态止损和防御ETF切换。",
        "dt": "2020-01-01 00:00:00",
        "etf_pool": [
          "518880.XSHG",
          "159980.XSHE",
          "159985.XSHE",
          "501018.XSHG",
          "513100.XSHG",
          "513500.XSHG",
          "513520.XSHG",
          "513030.XSHG",
          "513080.XSHG",
          "159920.XSHE",
          "510300.XSHG",
          "510500.XSHG",
          "510050.XSHG",
          "510210.XSHG",
          "159915.XSHE",
          "588080.XSHG",
          "159995.XSHE",
          "513050.XSHG",
          "159852.XSHE",
          "159845.XSHE",
          "515030.XSHG",
          "159806.XSHE",
          "516160.XSHG",
          "159928.XSHE",
          "511010.XSHG",
          "511880.XSHG"
        ],
        "event": "strategy_metadata",
        "filter_params": {
          "atr_exclude_defensive": true,
          "atr_multiplier": 2,
          "atr_period": 14,
          "atr_trailing_stop": false,
          "bollinger_lookback_days": 3,
          "bollinger_period": 20,
          "bollinger_std": 2.0,
          "ma_filter_condition": "above",
          "ma_long_period": 25,
          "ma_short_period": 5,
          "macd_fast_period": 12,
          "macd_filter_condition": "bullish",
          "macd_signal_period": 9,
          "macd_slow_period": 26,
          "rsi_lookback_days": 1,
          "rsi_period": 6,
          "rsi_threshold": 95,
          "short_momentum_threshold": 0.0,
          "volume_lookback_days": 7,
          "volume_threshold": 2.0
        },
        "filters": {
          "atr_stop_loss": true,
          "bollinger": false,
          "ma": false,
          "macd": false,
          "rsi": true,
          "short_momentum": true,
          "volume": false
        },
        "holdings_num": 1,
        "lookback_days": 25,
        "loss_filter_threshold": 0.97,
        "max_score_threshold": 5.0,
        "min_money": 5000,
        "min_score_threshold": 0.0,
        "short_lookback_days": 10,
        "stop_loss": 0.95,
        "strategy_code": "qmt_four_seasons_v3",
        "strategy_file": "qmt四季发财v3.py",
        "strategy_name": "QMT四季发财v3",
        "strategy_role": "community_strategy_audit_enhanced",
        "strategy_version": "v3-audit-log-20260619-r3-summary",
        "universe_size": 26
      }
    ]
  },
  "top_security_pnl": [
    {
      "security": "159852.XSHE",
      "n": 14,
      "pnl": 4297704.6,
      "fee": 25616.83,
      "win": 8,
      "win_rate": 0.5714285714285714
    },
    {
      "security": "501018.XSHG",
      "n": 26,
      "pnl": 3692591.34,
      "fee": 23775.589999999997,
      "win": 20,
      "win_rate": 0.7692307692307693
    },
    {
      "security": "518880.XSHG",
      "n": 31,
      "pnl": 3253939.1,
      "fee": 59114.70000000001,
      "win": 14,
      "win_rate": 0.45161290322580644
    },
    {
      "security": "159915.XSHE",
      "n": 24,
      "pnl": 2902100.9,
      "fee": 28550.879999999997,
      "win": 12,
      "win_rate": 0.5
    },
    {
      "security": "513520.XSHG",
      "n": 20,
      "pnl": 2867407.3,
      "fee": 29171.07,
      "win": 10,
      "win_rate": 0.5
    },
    {
      "security": "513030.XSHG",
      "n": 17,
      "pnl": 2075481.9000000001,
      "fee": 24053.85,
      "win": 14,
      "win_rate": 0.8235294117647058
    },
    {
      "security": "516160.XSHG",
      "n": 15,
      "pnl": 2067752.3,
      "fee": 26302.82,
      "win": 7,
      "win_rate": 0.4666666666666667
    },
    {
      "security": "513100.XSHG",
      "n": 29,
      "pnl": 1493062.5,
      "fee": 47088.770000000004,
      "win": 17,
      "win_rate": 0.5862068965517241
    }
  ],
  "bottom_security_pnl": [
    {
      "security": "588080.XSHG",
      "n": 12,
      "pnl": -1006.2000000000116,
      "fee": 11732.53,
      "win": 4,
      "win_rate": 0.3333333333333333
    },
    {
      "security": "159928.XSHE",
      "n": 18,
      "pnl": -22744.700000000084,
      "fee": 18540.97,
      "win": 8,
      "win_rate": 0.4444444444444444
    },
    {
      "security": "511010.XSHG",
      "n": 16,
      "pnl": -26058.499999999996,
      "fee": 18924.000000000004,
      "win": 6,
      "win_rate": 0.375
    },
    {
      "security": "510210.XSHG",
      "n": 7,
      "pnl": -243831.09999999998,
      "fee": 8080.1,
      "win": 1,
      "win_rate": 0.14285714285714285
    },
    {
      "security": "510050.XSHG",
      "n": 3,
      "pnl": -327701.9,
      "fee": 3100.65,
      "win": 1,
      "win_rate": 0.3333333333333333
    },
    {
      "security": "159980.XSHE",
      "n": 15,
      "pnl": -352282.10000000003,
      "fee": 12762.18,
      "win": 7,
      "win_rate": 0.4666666666666667
    },
    {
      "security": "510500.XSHG",
      "n": 5,
      "pnl": -368392.80000000005,
      "fee": 9230.810000000001,
      "win": 2,
      "win_rate": 0.4
    },
    {
      "security": "513080.XSHG",
      "n": 24,
      "pnl": -1729759.69,
      "fee": 10700.699999999997,
      "win": 9,
      "win_rate": 0.375
    }
  ]
}