{
  "source_path": "/Users/pechen/Downloads/淘宝运营速成指南：电商军规81讲 (贾真) (z-library.sk, 1lib.sk, z-lib.sk).epub",
  "sha256": "7f9add51c534fd8ad40d0bda3904188b88d9825d2a26fc57d7100332c1dca90a",
  "zip_file_count": 155,
  "opf_path": "OEBPS/content.opf",
  "ncx_path": "OEBPS/toc.ncx",
  "metadata": {
    "title": "淘宝运营速成指南：电商军规81讲",
    "creator": "贾真",
    "publisher": "电子工业出版社",
    "date": "2018-06-01",
    "language": "zh",
    "identifier": "urn:uuid:273fd756-62f2-4858-8d67-99e08f24bba9",
    "isbn": "978-7-121-33948-6",
    "identifiers": [
      {
        "value": "urn:uuid:273fd756-62f2-4858-8d67-99e08f24bba9",
        "id": "bookid"
      },
      {
        "value": "978-7-121-33948-6",
        "scheme": "ISBN"
      }
    ]
  },
  "counts": {
    "spine_items": 88,
    "toc_items": 88,
    "html_files": 88,
    "image_files": 60
  },
  "spine": [
    {
      "idref": "id_1",
      "href": "text00000.html",
      "path": "OEBPS/text00000.html",
      "media_type": "application/xhtml+xml",
      "properties": ""
    },
    {
      "idref": "id_2",
      "href": "text00001.html",
      "path": "OEBPS/text00001.html",
      "media_type": "application/xhtml+xml",
      "properties": ""
    },
    {
      "idref": "id_3",
      "href": "text00002.html",
      "path": "OEBPS/text00002.html",
      "media_type": "application/xhtml+xml",
      "properties": ""
    },
    {
      "idref": "id_4",
      "href": "text00003.html",
      "path": "OEBPS/text00003.html",
      "media_type": "application/xhtml+xml",
      "properties": ""
    },
    {
      "idref": "id_5",
      "href": "text00004.html",
      "path": "OEBPS/text00004.html",
      "media_type": "application/xhtml+xml",
      "properties": ""
    },
    {
      "idref": "id_6",
      "href": "text00005.html",
      "path": "OEBPS/text00005.html",
      "media_type": "application/xhtml+xml",
      "properties": ""
    },
    {
      "idref": "id_7",
      "href": "text00006.html",
      "path": "OEBPS/text00006.html",
      "media_type": "application/xhtml+xml",
      "properties": ""
    },
    {
      "idref": "id_8",
      "href": "text00007.html",
      "path": "OEBPS/text00007.html",
      "media_type": "application/xhtml+xml",
      "properties": ""
    },
    {
      "idref": "id_9",
      "href": "text00008.html",
      "path": "OEBPS/text00008.html",
      "media_type": "application/xhtml+xml",
      "properties": ""
    },
    {
      "idref": "id_10",
      "href": "text00009.html",
      "path": "OEBPS/text00009.html",
      "media_type": "application/xhtml+xml",
      "properties": ""
    },
    {
      "idref": "id_11",
      "href": "text00010.html",
      "path": "OEBPS/text00010.html",
      "media_type": "application/xhtml+xml",
      "properties": ""
    },
    {
      "idref": "id_12",
      "href": "text00011.html",
      "path": "OEBPS/text00011.html",
      "media_type": "application/xhtml+xml",
      "properties": ""
    },
    {
      "idref": "id_13",
      "href": "text00012.html",
      "path": "OEBPS/text00012.html",
      "media_type": "application/xhtml+xml",
      "properties": ""
    },
    {
      "idref": "id_14",
      "href": "text00013.html",
      "path": "OEBPS/text00013.html",
      "media_type": "application/xhtml+xml",
      "properties": ""
    },
    {
      "idref": "id_15",
      "href": "text00014.html",
      "path": "OEBPS/text00014.html",
      "media_type": "application/xhtml+xml",
      "properties": ""
    },
    {
      "idref": "id_16",
      "href": "text00015.html",
      "path": "OEBPS/text00015.html",
      "media_type": "application/xhtml+xml",
      "properties": ""
    },
    {
      "idref": "id_17",
      "href": "text00016.html",
      "path": "OEBPS/text00016.html",
      "media_type": "application/xhtml+xml",
      "properties": ""
    },
    {
      "idref": "id_18",
      "href": "text00017.html",
      "path": "OEBPS/text00017.html",
      "media_type": "application/xhtml+xml",
      "properties": ""
    },
    {
      "idref": "id_19",
      "href": "text00018.html",
      "path": "OEBPS/text00018.html",
      "media_type": "application/xhtml+xml",
      "properties": ""
    },
    {
      "idref": "id_20",
      "href": "text00019.html",
      "path": "OEBPS/text00019.html",
      "media_type": "application/xhtml+xml",
      "properties": ""
    },
    {
      "idref": "id_21",
      "href": "text00020.html",
      "path": "OEBPS/text00020.html",
      "media_type": "application/xhtml+xml",
      "properties": ""
    },
    {
      "idref": "id_22",
      "href": "text00021.html",
      "path": "OEBPS/text00021.html",
      "media_type": "application/xhtml+xml",
      "properties": ""
    },
    {
      "idref": "id_23",
      "href": "text00022.html",
      "path": "OEBPS/text00022.html",
      "media_type": "application/xhtml+xml",
      "properties": ""
    },
    {
      "idref": "id_24",
      "href": "text00023.html",
      "path": "OEBPS/text00023.html",
      "media_type": "application/xhtml+xml",
      "properties": ""
    },
    {
      "idref": "id_25",
      "href": "text00024.html",
      "path": "OEBPS/text00024.html",
      "media_type": "application/xhtml+xml",
      "properties": ""
    },
    {
      "idref": "id_26",
      "href": "text00025.html",
      "path": "OEBPS/text00025.html",
      "media_type": "application/xhtml+xml",
      "properties": ""
    },
    {
      "idref": "id_27",
      "href": "text00026.html",
      "path": "OEBPS/text00026.html",
      "media_type": "application/xhtml+xml",
      "properties": ""
    },
    {
      "idref": "id_28",
      "href": "text00027.html",
      "path": "OEBPS/text00027.html",
      "media_type": "application/xhtml+xml",
      "properties": ""
    },
    {
      "idref": "id_29",
      "href": "text00028.html",
      "path": "OEBPS/text00028.html",
      "media_type": "application/xhtml+xml",
      "properties": ""
    },
    {
      "idref": "id_30",
      "href": "text00029.html",
      "path": "OEBPS/text00029.html",
      "media_type": "application/xhtml+xml",
      "properties": ""
    },
    {
      "idref": "id_31",
      "href": "text00030.html",
      "path": "OEBPS/text00030.html",
      "media_type": "application/xhtml+xml",
      "properties": ""
    },
    {
      "idref": "id_32",
      "href": "text00031.html",
      "path": "OEBPS/text00031.html",
      "media_type": "application/xhtml+xml",
      "properties": ""
    },
    {
      "idref": "id_33",
      "href": "text00032.html",
      "path": "OEBPS/text00032.html",
      "media_type": "application/xhtml+xml",
      "properties": ""
    },
    {
      "idref": "id_34",
      "href": "text00033.html",
      "path": "OEBPS/text00033.html",
      "media_type": "application/xhtml+xml",
      "properties": ""
    },
    {
      "idref": "id_35",
      "href": "text00034.html",
      "path": "OEBPS/text00034.html",
      "media_type": "application/xhtml+xml",
      "properties": ""
    },
    {
      "idref": "id_36",
      "href": "text00035.html",
      "path": "OEBPS/text00035.html",
      "media_type": "application/xhtml+xml",
      "properties": ""
    },
    {
      "idref": "id_37",
      "href": "text00036.html",
      "path": "OEBPS/text00036.html",
      "media_type": "application/xhtml+xml",
      "properties": ""
    },
    {
      "idref": "id_38",
      "href": "text00037.html",
      "path": "OEBPS/text00037.html",
      "media_type": "application/xhtml+xml",
      "properties": ""
    },
    {
      "idref": "id_39",
      "href": "text00038.html",
      "path": "OEBPS/text00038.html",
      "media_type": "application/xhtml+xml",
      "properties": ""
    },
    {
      "idref": "id_40",
      "href": "text00039.html",
      "path": "OEBPS/text00039.html",
      "media_type": "application/xhtml+xml",
      "properties": ""
    },
    {
      "idref": "id_41",
      "href": "text00040.html",
      "path": "OEBPS/text00040.html",
      "media_type": "application/xhtml+xml",
      "properties": ""
    },
    {
      "idref": "id_42",
      "href": "text00041.html",
      "path": "OEBPS/text00041.html",
      "media_type": "application/xhtml+xml",
      "properties": ""
    },
    {
      "idref": "id_43",
      "href": "text00042.html",
      "path": "OEBPS/text00042.html",
      "media_type": "application/xhtml+xml",
      "properties": ""
    },
    {
      "idref": "id_44",
      "href": "text00043.html",
      "path": "OEBPS/text00043.html",
      "media_type": "application/xhtml+xml",
      "properties": ""
    },
    {
      "idref": "id_45",
      "href": "text00044.html",
      "path": "OEBPS/text00044.html",
      "media_type": "application/xhtml+xml",
      "properties": ""
    },
    {
      "idref": "id_46",
      "href": "text00045.html",
      "path": "OEBPS/text00045.html",
      "media_type": "application/xhtml+xml",
      "properties": ""
    },
    {
      "idref": "id_47",
      "href": "text00046.html",
      "path": "OEBPS/text00046.html",
      "media_type": "application/xhtml+xml",
      "properties": ""
    },
    {
      "idref": "id_48",
      "href": "text00047.html",
      "path": "OEBPS/text00047.html",
      "media_type": "application/xhtml+xml",
      "properties": ""
    },
    {
      "idref": "id_49",
      "href": "text00048.html",
      "path": "OEBPS/text00048.html",
      "media_type": "application/xhtml+xml",
      "properties": ""
    },
    {
      "idref": "id_50",
      "href": "text00049.html",
      "path": "OEBPS/text00049.html",
      "media_type": "application/xhtml+xml",
      "properties": ""
    },
    {
      "idref": "id_51",
      "href": "text00050.html",
      "path": "OEBPS/text00050.html",
      "media_type": "application/xhtml+xml",
      "properties": ""
    },
    {
      "idref": "id_52",
      "href": "text00051.html",
      "path": "OEBPS/text00051.html",
      "media_type": "application/xhtml+xml",
      "properties": ""
    },
    {
      "idref": "id_53",
      "href": "text00052.html",
      "path": "OEBPS/text00052.html",
      "media_type": "application/xhtml+xml",
      "properties": ""
    },
    {
      "idref": "id_54",
      "href": "text00053.html",
      "path": "OEBPS/text00053.html",
      "media_type": "application/xhtml+xml",
      "properties": ""
    },
    {
      "idref": "id_55",
      "href": "text00054.html",
      "path": "OEBPS/text00054.html",
      "media_type": "application/xhtml+xml",
      "properties": ""
    },
    {
      "idref": "id_56",
      "href": "text00055.html",
      "path": "OEBPS/text00055.html",
      "media_type": "application/xhtml+xml",
      "properties": ""
    },
    {
      "idref": "id_57",
      "href": "text00056.html",
      "path": "OEBPS/text00056.html",
      "media_type": "application/xhtml+xml",
      "properties": ""
    },
    {
      "idref": "id_58",
      "href": "text00057.html",
      "path": "OEBPS/text00057.html",
      "media_type": "application/xhtml+xml",
      "properties": ""
    },
    {
      "idref": "id_59",
      "href": "text00058.html",
      "path": "OEBPS/text00058.html",
      "media_type": "application/xhtml+xml",
      "properties": ""
    },
    {
      "idref": "id_60",
      "href": "text00059.html",
      "path": "OEBPS/text00059.html",
      "media_type": "application/xhtml+xml",
      "properties": ""
    },
    {
      "idref": "id_61",
      "href": "text00060.html",
      "path": "OEBPS/text00060.html",
      "media_type": "application/xhtml+xml",
      "properties": ""
    },
    {
      "idref": "id_62",
      "href": "text00061.html",
      "path": "OEBPS/text00061.html",
      "media_type": "application/xhtml+xml",
      "properties": ""
    },
    {
      "idref": "id_63",
      "href": "text00062.html",
      "path": "OEBPS/text00062.html",
      "media_type": "application/xhtml+xml",
      "properties": ""
    },
    {
      "idref": "id_64",
      "href": "text00063.html",
      "path": "OEBPS/text00063.html",
      "media_type": "application/xhtml+xml",
      "properties": ""
    },
    {
      "idref": "id_65",
      "href": "text00064.html",
      "path": "OEBPS/text00064.html",
      "media_type": "application/xhtml+xml",
      "properties": ""
    },
    {
      "idref": "id_66",
      "href": "text00065.html",
      "path": "OEBPS/text00065.html",
      "media_type": "application/xhtml+xml",
      "properties": ""
    },
    {
      "idref": "id_67",
      "href": "text00066.html",
      "path": "OEBPS/text00066.html",
      "media_type": "application/xhtml+xml",
      "properties": ""
    },
    {
      "idref": "id_68",
      "href": "text00067.html",
      "path": "OEBPS/text00067.html",
      "media_type": "application/xhtml+xml",
      "properties": ""
    },
    {
      "idref": "id_69",
      "href": "text00068.html",
      "path": "OEBPS/text00068.html",
      "media_type": "application/xhtml+xml",
      "properties": ""
    },
    {
      "idref": "id_70",
      "href": "text00069.html",
      "path": "OEBPS/text00069.html",
      "media_type": "application/xhtml+xml",
      "properties": ""
    },
    {
      "idref": "id_71",
      "href": "text00070.html",
      "path": "OEBPS/text00070.html",
      "media_type": "application/xhtml+xml",
      "properties": ""
    },
    {
      "idref": "id_72",
      "href": "text00071.html",
      "path": "OEBPS/text00071.html",
      "media_type": "application/xhtml+xml",
      "properties": ""
    },
    {
      "idref": "id_73",
      "href": "text00072.html",
      "path": "OEBPS/text00072.html",
      "media_type": "application/xhtml+xml",
      "properties": ""
    },
    {
      "idref": "id_74",
      "href": "text00073.html",
      "path": "OEBPS/text00073.html",
      "media_type": "application/xhtml+xml",
      "properties": ""
    },
    {
      "idref": "id_75",
      "href": "text00074.html",
      "path": "OEBPS/text00074.html",
      "media_type": "application/xhtml+xml",
      "properties": ""
    },
    {
      "idref": "id_76",
      "href": "text00075.html",
      "path": "OEBPS/text00075.html",
      "media_type": "application/xhtml+xml",
      "properties": ""
    },
    {
      "idref": "id_77",
      "href": "text00076.html",
      "path": "OEBPS/text00076.html",
      "media_type": "application/xhtml+xml",
      "properties": ""
    },
    {
      "idref": "id_78",
      "href": "text00077.html",
      "path": "OEBPS/text00077.html",
      "media_type": "application/xhtml+xml",
      "properties": ""
    },
    {
      "idref": "id_79",
      "href": "text00078.html",
      "path": "OEBPS/text00078.html",
      "media_type": "application/xhtml+xml",
      "properties": ""
    },
    {
      "idref": "id_80",
      "href": "text00079.html",
      "path": "OEBPS/text00079.html",
      "media_type": "application/xhtml+xml",
      "properties": ""
    },
    {
      "idref": "id_81",
      "href": "text00080.html",
      "path": "OEBPS/text00080.html",
      "media_type": "application/xhtml+xml",
      "properties": ""
    },
    {
      "idref": "id_82",
      "href": "text00081.html",
      "path": "OEBPS/text00081.html",
      "media_type": "application/xhtml+xml",
      "properties": ""
    },
    {
      "idref": "id_83",
      "href": "text00082.html",
      "path": "OEBPS/text00082.html",
      "media_type": "application/xhtml+xml",
      "properties": ""
    },
    {
      "idref": "id_84",
      "href": "text00083.html",
      "path": "OEBPS/text00083.html",
      "media_type": "application/xhtml+xml",
      "properties": ""
    },
    {
      "idref": "id_85",
      "href": "text00084.html",
      "path": "OEBPS/text00084.html",
      "media_type": "application/xhtml+xml",
      "properties": ""
    },
    {
      "idref": "id_86",
      "href": "text00085.html",
      "path": "OEBPS/text00085.html",
      "media_type": "application/xhtml+xml",
      "properties": ""
    },
    {
      "idref": "id_87",
      "href": "text00086.html",
      "path": "OEBPS/text00086.html",
      "media_type": "application/xhtml+xml",
      "properties": ""
    },
    {
      "idref": "id_88",
      "href": "text00087.html",
      "path": "OEBPS/text00087.html",
      "media_type": "application/xhtml+xml",
      "properties": ""
    }
  ],
  "toc": [
    {
      "id": "id1",
      "play_order": 1,
      "depth": 1,
      "title": "作者简介",
      "src": "text00000.html#A43480001-1ba4-40af-af73-df038a7f02ce",
      "file": "OEBPS/text00000.html",
      "fragment": "A43480001-1ba4-40af-af73-df038a7f02ce"
    },
    {
      "id": "id2",
      "play_order": 2,
      "depth": 1,
      "title": "文前插图",
      "src": "text00001.html#A65660002-fd2d-444c-8618-69af74a8fd21",
      "file": "OEBPS/text00001.html",
      "fragment": "A65660002-fd2d-444c-8618-69af74a8fd21"
    },
    {
      "id": "id3",
      "play_order": 3,
      "depth": 1,
      "title": "版权页",
      "src": "text00002.html",
      "file": "OEBPS/text00002.html",
      "fragment": ""
    },
    {
      "id": "id4",
      "play_order": 4,
      "depth": 1,
      "title": "前言",
      "src": "text00003.html#A73eb0005-93aa-4189-811f-eb69e4d0652a",
      "file": "OEBPS/text00003.html",
      "fragment": "A73eb0005-93aa-4189-811f-eb69e4d0652a"
    },
    {
      "id": "id5",
      "play_order": 5,
      "depth": 1,
      "title": "目录",
      "src": "text00004.html",
      "file": "OEBPS/text00004.html",
      "fragment": ""
    },
    {
      "id": "id6",
      "play_order": 6,
      "depth": 1,
      "title": "第1篇 电商军规",
      "src": "text00005.html#A8b0470ce-0e55-4997-97f4-e9ff89ddf13a",
      "file": "OEBPS/text00005.html",
      "fragment": "A8b0470ce-0e55-4997-97f4-e9ff89ddf13a"
    },
    {
      "id": "id7",
      "play_order": 7,
      "depth": 2,
      "title": "1 亲力亲为",
      "src": "text00006.html#Aeec8e368-5de7-495a-8832-fcc12eb5fc66",
      "file": "OEBPS/text00006.html",
      "fragment": "Aeec8e368-5de7-495a-8832-fcc12eb5fc66"
    },
    {
      "id": "id8",
      "play_order": 8,
      "depth": 2,
      "title": "2 学以致用",
      "src": "text00007.html#A6f7bb54e-b79c-4c59-a481-b7ed033d4abe",
      "file": "OEBPS/text00007.html",
      "fragment": "A6f7bb54e-b79c-4c59-a481-b7ed033d4abe"
    },
    {
      "id": "id9",
      "play_order": 9,
      "depth": 2,
      "title": "3 一人百万",
      "src": "text00008.html#A33434f50-0080-4e99-aa2f-d066cd91fbda",
      "file": "OEBPS/text00008.html",
      "fragment": "A33434f50-0080-4e99-aa2f-d066cd91fbda"
    },
    {
      "id": "id10",
      "play_order": 10,
      "depth": 2,
      "title": "4 专注制胜",
      "src": "text00009.html#A09e49aa2-f84d-4231-adc0-b43a6f105769",
      "file": "OEBPS/text00009.html",
      "fragment": "A09e49aa2-f84d-4231-adc0-b43a6f105769"
    },
    {
      "id": "id11",
      "play_order": 11,
      "depth": 2,
      "title": "5 守正出奇",
      "src": "text00010.html#A78e42344-ea30-4865-bdfa-9ee528170b8a",
      "file": "OEBPS/text00010.html",
      "fragment": "A78e42344-ea30-4865-bdfa-9ee528170b8a"
    },
    {
      "id": "id12",
      "play_order": 12,
      "depth": 2,
      "title": "6 创新",
      "src": "text00011.html#A9d7a3063-e364-4a87-a2bf-dcddf85a1156",
      "file": "OEBPS/text00011.html",
      "fragment": "A9d7a3063-e364-4a87-a2bf-dcddf85a1156"
    },
    {
      "id": "id13",
      "play_order": 13,
      "depth": 2,
      "title": "7 好名字好生意",
      "src": "text00012.html#Aca8aadd2-dd2b-4631-a054-9e379336f25f",
      "file": "OEBPS/text00012.html",
      "fragment": "Aca8aadd2-dd2b-4631-a054-9e379336f25f"
    },
    {
      "id": "id14",
      "play_order": 14,
      "depth": 2,
      "title": "8 维护老客户",
      "src": "text00013.html#A128adabd-e944-484f-8354-f6e1fbdc1dba",
      "file": "OEBPS/text00013.html",
      "fragment": "A128adabd-e944-484f-8354-f6e1fbdc1dba"
    },
    {
      "id": "id15",
      "play_order": 15,
      "depth": 2,
      "title": "9 不留退路",
      "src": "text00014.html#Ae8cc0a7f-8dd6-406f-bcd3-e547291197ac",
      "file": "OEBPS/text00014.html",
      "fragment": "Ae8cc0a7f-8dd6-406f-bcd3-e547291197ac"
    },
    {
      "id": "id16",
      "play_order": 16,
      "depth": 2,
      "title": "10 解决人才困境",
      "src": "text00015.html#Ac1435302-2773-4c0f-a27e-0942e1305277",
      "file": "OEBPS/text00015.html",
      "fragment": "Ac1435302-2773-4c0f-a27e-0942e1305277"
    },
    {
      "id": "id17",
      "play_order": 17,
      "depth": 2,
      "title": "11 走品牌之路",
      "src": "text00016.html#Afbd1e665-cd2e-4729-a9b9-206fdc101f04",
      "file": "OEBPS/text00016.html",
      "fragment": "Afbd1e665-cd2e-4729-a9b9-206fdc101f04"
    },
    {
      "id": "id18",
      "play_order": 18,
      "depth": 2,
      "title": "12 跳离舒适区",
      "src": "text00017.html#A667726fd-c1d9-4280-aa31-126fdcb4cb29",
      "file": "OEBPS/text00017.html",
      "fragment": "A667726fd-c1d9-4280-aa31-126fdcb4cb29"
    },
    {
      "id": "id19",
      "play_order": 19,
      "depth": 2,
      "title": "13 别迷信“大神”",
      "src": "text00018.html#A404f3c5e-2720-48bf-ba89-417469ea0ce9",
      "file": "OEBPS/text00018.html",
      "fragment": "A404f3c5e-2720-48bf-ba89-417469ea0ce9"
    },
    {
      "id": "id20",
      "play_order": 20,
      "depth": 2,
      "title": "14 明确定位",
      "src": "text00019.html#Ae3a7e09b-52dd-4de8-87aa-ab39323bcf28",
      "file": "OEBPS/text00019.html",
      "fragment": "Ae3a7e09b-52dd-4de8-87aa-ab39323bcf28"
    },
    {
      "id": "id21",
      "play_order": 21,
      "depth": 2,
      "title": "15 会打价格战",
      "src": "text00020.html#A956bb0b1-385d-4760-a4f1-34a7a6c38134",
      "file": "OEBPS/text00020.html",
      "fragment": "A956bb0b1-385d-4760-a4f1-34a7a6c38134"
    },
    {
      "id": "id22",
      "play_order": 22,
      "depth": 2,
      "title": "16 故事营销",
      "src": "text00021.html#A9841513c-c500-43a4-b278-0695b4252a5c",
      "file": "OEBPS/text00021.html",
      "fragment": "A9841513c-c500-43a4-b278-0695b4252a5c"
    },
    {
      "id": "id23",
      "play_order": 23,
      "depth": 2,
      "title": "17 一张一弛",
      "src": "text00022.html#Ab4b58040-f377-4142-91a5-8a747b39dcdd",
      "file": "OEBPS/text00022.html",
      "fragment": "Ab4b58040-f377-4142-91a5-8a747b39dcdd"
    },
    {
      "id": "id24",
      "play_order": 24,
      "depth": 2,
      "title": "18 热点营销",
      "src": "text00023.html#A27262ab1-47d7-45db-a8f3-1cc62370ede4",
      "file": "OEBPS/text00023.html",
      "fragment": "A27262ab1-47d7-45db-a8f3-1cc62370ede4"
    },
    {
      "id": "id25",
      "play_order": 25,
      "depth": 2,
      "title": "19 规避风险",
      "src": "text00024.html#A90966d2a-6247-41f3-a956-d9dde178fc22",
      "file": "OEBPS/text00024.html",
      "fragment": "A90966d2a-6247-41f3-a956-d9dde178fc22"
    },
    {
      "id": "id26",
      "play_order": 26,
      "depth": 2,
      "title": "20 心要仁慈刀要快",
      "src": "text00025.html#A1461630d-eae1-4487-aff2-1ec79ab87c18",
      "file": "OEBPS/text00025.html",
      "fragment": "A1461630d-eae1-4487-aff2-1ec79ab87c18"
    },
    {
      "id": "id27",
      "play_order": 27,
      "depth": 2,
      "title": "21 股权激励",
      "src": "text00026.html#Aec733af0-f32e-4674-86b9-87def9ff9e96",
      "file": "OEBPS/text00026.html",
      "fragment": "Aec733af0-f32e-4674-86b9-87def9ff9e96"
    },
    {
      "id": "id28",
      "play_order": 28,
      "depth": 2,
      "title": "22 走向线下",
      "src": "text00027.html#Ac31cf0ba-ba28-41f4-a753-331fef8f7172",
      "file": "OEBPS/text00027.html",
      "fragment": "Ac31cf0ba-ba28-41f4-a753-331fef8f7172"
    },
    {
      "id": "id29",
      "play_order": 29,
      "depth": 2,
      "title": "23 打造企业文化",
      "src": "text00028.html#A3d22cb1d-83b3-4d62-ab25-e70282bbfad3",
      "file": "OEBPS/text00028.html",
      "fragment": "A3d22cb1d-83b3-4d62-ab25-e70282bbfad3"
    },
    {
      "id": "id30",
      "play_order": 30,
      "depth": 2,
      "title": "24 问题即机会",
      "src": "text00029.html#A40ffd896-c083-4ead-8838-565936ea7443",
      "file": "OEBPS/text00029.html",
      "fragment": "A40ffd896-c083-4ead-8838-565936ea7443"
    },
    {
      "id": "id31",
      "play_order": 31,
      "depth": 2,
      "title": "25 五条忠告",
      "src": "text00030.html#A5b697486-119b-4420-939b-bb5e5fc9ad4f",
      "file": "OEBPS/text00030.html",
      "fragment": "A5b697486-119b-4420-939b-bb5e5fc9ad4f"
    },
    {
      "id": "id32",
      "play_order": 32,
      "depth": 1,
      "title": "第2篇 运营技巧",
      "src": "text00031.html#Aaddd5153-17ec-4876-b3b5-e54cb3c9b116",
      "file": "OEBPS/text00031.html",
      "fragment": "Aaddd5153-17ec-4876-b3b5-e54cb3c9b116"
    },
    {
      "id": "id33",
      "play_order": 33,
      "depth": 2,
      "title": "1 标题优化",
      "src": "text00032.html#A714dbb43-4c81-448f-b5a1-7a822ceb6b44",
      "file": "OEBPS/text00032.html",
      "fragment": "A714dbb43-4c81-448f-b5a1-7a822ceb6b44"
    },
    {
      "id": "id34",
      "play_order": 34,
      "depth": 2,
      "title": "2 主图优化",
      "src": "text00033.html#A18568b45-aa47-41a3-8937-fa8084e9f7e1",
      "file": "OEBPS/text00033.html",
      "fragment": "A18568b45-aa47-41a3-8937-fa8084e9f7e1"
    },
    {
      "id": "id35",
      "play_order": 35,
      "depth": 2,
      "title": "3 详情页策划",
      "src": "text00034.html#Ac3036429-674b-477e-9d5e-03edccce829a",
      "file": "OEBPS/text00034.html",
      "fragment": "Ac3036429-674b-477e-9d5e-03edccce829a"
    },
    {
      "id": "id36",
      "play_order": 36,
      "depth": 2,
      "title": "4 直通车推广",
      "src": "text00035.html#Adfae0025-583c-4876-83ae-ba6242dbddf9",
      "file": "OEBPS/text00035.html",
      "fragment": "Adfae0025-583c-4876-83ae-ba6242dbddf9"
    },
    {
      "id": "id37",
      "play_order": 37,
      "depth": 2,
      "title": "5 钻展推广策略",
      "src": "text00036.html#A31fedaf1-7407-4b17-9297-79887fcf9fea",
      "file": "OEBPS/text00036.html",
      "fragment": "A31fedaf1-7407-4b17-9297-79887fcf9fea"
    },
    {
      "id": "id38",
      "play_order": 38,
      "depth": 2,
      "title": "6 淘宝店微信策略",
      "src": "text00037.html#A49d532f9-14c1-4043-abe3-aef4e4040152",
      "file": "OEBPS/text00037.html",
      "fragment": "A49d532f9-14c1-4043-abe3-aef4e4040152"
    },
    {
      "id": "id39",
      "play_order": 39,
      "depth": 2,
      "title": "7 新淘客生态：团长、卖家、个人淘客",
      "src": "text00038.html#Ad041c829-16b3-4c77-a37e-a70996066a6f",
      "file": "OEBPS/text00038.html",
      "fragment": "Ad041c829-16b3-4c77-a37e-a70996066a6f"
    },
    {
      "id": "id40",
      "play_order": 40,
      "depth": 2,
      "title": "8 “双11”大促",
      "src": "text00039.html#A31b12bef-19ca-4e01-87c9-13bb782cf9b1",
      "file": "OEBPS/text00039.html",
      "fragment": "A31b12bef-19ca-4e01-87c9-13bb782cf9b1"
    },
    {
      "id": "id41",
      "play_order": 41,
      "depth": 2,
      "title": "9 淘宝达人",
      "src": "text00040.html#A39e5bb43-5a53-4ad8-bf0d-e92381d20d73",
      "file": "OEBPS/text00040.html",
      "fragment": "A39e5bb43-5a53-4ad8-bf0d-e92381d20d73"
    },
    {
      "id": "id42",
      "play_order": 42,
      "depth": 2,
      "title": "10 直播和内容营销",
      "src": "text00041.html#A35c7a29d-313f-43e1-9a81-f6e83088ec40",
      "file": "OEBPS/text00041.html",
      "fragment": "A35c7a29d-313f-43e1-9a81-f6e83088ec40"
    },
    {
      "id": "id43",
      "play_order": 43,
      "depth": 2,
      "title": "11 关联和促销，流量不变，提高销售额",
      "src": "text00042.html#Ac6f50496-72c9-4c54-840f-459d72ed0e74",
      "file": "OEBPS/text00042.html",
      "fragment": "Ac6f50496-72c9-4c54-840f-459d72ed0e74"
    },
    {
      "id": "id44",
      "play_order": 44,
      "depth": 2,
      "title": "12 淘宝搜索工作原理",
      "src": "text00043.html#A5887955c-fd20-4140-b811-0179a3ddefba",
      "file": "OEBPS/text00043.html",
      "fragment": "A5887955c-fd20-4140-b811-0179a3ddefba"
    },
    {
      "id": "id45",
      "play_order": 45,
      "depth": 2,
      "title": "13 单品数据异常的自我诊断（上）",
      "src": "text00044.html#A0251d05b-42f6-4c18-adc7-3a1df6709de1",
      "file": "OEBPS/text00044.html",
      "fragment": "A0251d05b-42f6-4c18-adc7-3a1df6709de1"
    },
    {
      "id": "id46",
      "play_order": 46,
      "depth": 2,
      "title": "14 单品数据异常的自我诊断（下）",
      "src": "text00045.html#A34312406-7cbb-4f64-9a36-4d41afdb9535",
      "file": "OEBPS/text00045.html",
      "fragment": "A34312406-7cbb-4f64-9a36-4d41afdb9535"
    },
    {
      "id": "id47",
      "play_order": 47,
      "depth": 2,
      "title": "15 谈刷单",
      "src": "text00046.html#Acaecdda9-d841-470c-ae5c-065544a246c6",
      "file": "OEBPS/text00046.html",
      "fragment": "Acaecdda9-d841-470c-ae5c-065544a246c6"
    },
    {
      "id": "id48",
      "play_order": 48,
      "depth": 2,
      "title": "16 多店铺运营的弊端",
      "src": "text00047.html#Afd2a3be6-59a4-409e-8e75-f90da7e19a4a",
      "file": "OEBPS/text00047.html",
      "fragment": "Afd2a3be6-59a4-409e-8e75-f90da7e19a4a"
    },
    {
      "id": "id49",
      "play_order": 49,
      "depth": 2,
      "title": "17 如何提升店铺服务体验",
      "src": "text00048.html#Abb14f226-3d5f-4a33-9af2-df06533551fe",
      "file": "OEBPS/text00048.html",
      "fragment": "Abb14f226-3d5f-4a33-9af2-df06533551fe"
    },
    {
      "id": "id50",
      "play_order": 50,
      "depth": 2,
      "title": "18 售前客服绩效，打造“狼性”客服",
      "src": "text00049.html#A6814123f-6cbe-42fb-9af9-5b7dfd2215b8",
      "file": "OEBPS/text00049.html",
      "fragment": "A6814123f-6cbe-42fb-9af9-5b7dfd2215b8"
    },
    {
      "id": "id51",
      "play_order": 51,
      "depth": 2,
      "title": "19 如何做老客户维护",
      "src": "text00050.html#A72080d83-782f-4b83-abdb-7b6cb5d1ed8e",
      "file": "OEBPS/text00050.html",
      "fragment": "A72080d83-782f-4b83-abdb-7b6cb5d1ed8e"
    },
    {
      "id": "id52",
      "play_order": 52,
      "depth": 2,
      "title": "20 店铺上新品的方法和思路",
      "src": "text00051.html#A943b8320-b894-4953-a459-1b9a5651f80b",
      "file": "OEBPS/text00051.html",
      "fragment": "A943b8320-b894-4953-a459-1b9a5651f80b"
    },
    {
      "id": "id53",
      "play_order": 53,
      "depth": 2,
      "title": "21 数据选品",
      "src": "text00052.html#A2e3c13d5-fb01-4bdc-9dab-b670a957c974",
      "file": "OEBPS/text00052.html",
      "fragment": "A2e3c13d5-fb01-4bdc-9dab-b670a957c974"
    },
    {
      "id": "id54",
      "play_order": 54,
      "depth": 2,
      "title": "22 推新品的思考1——新品权重",
      "src": "text00053.html#A5753d750-3323-45de-b584-5cb4c52e2bc8",
      "file": "OEBPS/text00053.html",
      "fragment": "A5753d750-3323-45de-b584-5cb4c52e2bc8"
    },
    {
      "id": "id55",
      "play_order": 55,
      "depth": 2,
      "title": "23 推新品的思考2——新品赛马期",
      "src": "text00054.html#A4a276c35-4500-41fb-855a-60729d9f3b2b",
      "file": "OEBPS/text00054.html",
      "fragment": "A4a276c35-4500-41fb-855a-60729d9f3b2b"
    },
    {
      "id": "id56",
      "play_order": 56,
      "depth": 2,
      "title": "24 店铺定位",
      "src": "text00055.html#A7d95fabb-70cc-4d64-9589-31af3fca66e2",
      "file": "OEBPS/text00055.html",
      "fragment": "A7d95fabb-70cc-4d64-9589-31af3fca66e2"
    },
    {
      "id": "id57",
      "play_order": 57,
      "depth": 2,
      "title": "25 从iPhone X的热销，看淘宝爆款的未来",
      "src": "text00056.html#A7adfee63-8d32-465f-8ffb-a78f5ec8df71",
      "file": "OEBPS/text00056.html",
      "fragment": "A7adfee63-8d32-465f-8ffb-a78f5ec8df71"
    },
    {
      "id": "id58",
      "play_order": 58,
      "depth": 2,
      "title": "26 店铺首页设计逻辑",
      "src": "text00057.html#A20fd9d15-bcb0-4844-9dc4-2bd904eed7fa",
      "file": "OEBPS/text00057.html",
      "fragment": "A20fd9d15-bcb0-4844-9dc4-2bd904eed7fa"
    },
    {
      "id": "id59",
      "play_order": 59,
      "depth": 2,
      "title": "27 连贯性运营",
      "src": "text00058.html#A78994530-cb5f-42ac-ac29-64ab05f9a2a7",
      "file": "OEBPS/text00058.html",
      "fragment": "A78994530-cb5f-42ac-ac29-64ab05f9a2a7"
    },
    {
      "id": "id60",
      "play_order": 60,
      "depth": 2,
      "title": "28 提升转化率——三次催付交接表",
      "src": "text00059.html#A1b458871-eef2-43cd-b520-44ce71299c31",
      "file": "OEBPS/text00059.html",
      "fragment": "A1b458871-eef2-43cd-b520-44ce71299c31"
    },
    {
      "id": "id61",
      "play_order": 61,
      "depth": 2,
      "title": "29 电商供应链",
      "src": "text00060.html#Ac178e894-a142-40b1-a8c3-0caa3cca316c",
      "file": "OEBPS/text00060.html",
      "fragment": "Ac178e894-a142-40b1-a8c3-0caa3cca316c"
    },
    {
      "id": "id62",
      "play_order": 62,
      "depth": 2,
      "title": "30 电商定价策略（上）",
      "src": "text00061.html#Af5c26f7d-d1b3-47a9-b6fd-161b7cb80bce",
      "file": "OEBPS/text00061.html",
      "fragment": "Af5c26f7d-d1b3-47a9-b6fd-161b7cb80bce"
    },
    {
      "id": "id63",
      "play_order": 63,
      "depth": 2,
      "title": "31 电商定价策略（下）",
      "src": "text00062.html#A46fff6d9-ec48-429f-b8bf-a14fd31cb591",
      "file": "OEBPS/text00062.html",
      "fragment": "A46fff6d9-ec48-429f-b8bf-a14fd31cb591"
    },
    {
      "id": "id64",
      "play_order": 64,
      "depth": 2,
      "title": "32 人群切分",
      "src": "text00063.html#A51def618-a97f-4c2a-a9ff-97c54fa7c280",
      "file": "OEBPS/text00063.html",
      "fragment": "A51def618-a97f-4c2a-a9ff-97c54fa7c280"
    },
    {
      "id": "id65",
      "play_order": 65,
      "depth": 2,
      "title": "33 卖点策划（上）",
      "src": "text00064.html#A5bdf8190-8601-486e-bb22-3ec9d75f05d6",
      "file": "OEBPS/text00064.html",
      "fragment": "A5bdf8190-8601-486e-bb22-3ec9d75f05d6"
    },
    {
      "id": "id66",
      "play_order": 66,
      "depth": 2,
      "title": "34 卖点策划（下）",
      "src": "text00065.html#A0faccd56-25c1-45b3-9cd5-6cc3c5644ce0",
      "file": "OEBPS/text00065.html",
      "fragment": "A0faccd56-25c1-45b3-9cd5-6cc3c5644ce0"
    },
    {
      "id": "id67",
      "play_order": 67,
      "depth": 2,
      "title": "35 那些年，我们做死的爆款（上）",
      "src": "text00066.html#Ab8972c17-7c8c-44d7-a2cc-a184e4a35fa7",
      "file": "OEBPS/text00066.html",
      "fragment": "Ab8972c17-7c8c-44d7-a2cc-a184e4a35fa7"
    },
    {
      "id": "id68",
      "play_order": 68,
      "depth": 2,
      "title": "36 那些年，我们做死的爆款（下）",
      "src": "text00067.html#A1e52573b-a9fa-400b-a8c5-3f59ad030169",
      "file": "OEBPS/text00067.html",
      "fragment": "A1e52573b-a9fa-400b-a8c5-3f59ad030169"
    },
    {
      "id": "id69",
      "play_order": 69,
      "depth": 2,
      "title": "37 仓库发货流程优化",
      "src": "text00068.html#A0112da08-a79c-42df-87b2-a222b74f11ba",
      "file": "OEBPS/text00068.html",
      "fragment": "A0112da08-a79c-42df-87b2-a222b74f11ba"
    },
    {
      "id": "id70",
      "play_order": 70,
      "depth": 2,
      "title": "38 美工绩效",
      "src": "text00069.html#Ac4a08fb8-09da-4500-9266-40a72614c78f",
      "file": "OEBPS/text00069.html",
      "fragment": "Ac4a08fb8-09da-4500-9266-40a72614c78f"
    },
    {
      "id": "id71",
      "play_order": 71,
      "depth": 2,
      "title": "39 竞品分析",
      "src": "text00070.html#A02203f04-4d2a-4aeb-b2db-16eb0dbe48b5",
      "file": "OEBPS/text00070.html",
      "fragment": "A02203f04-4d2a-4aeb-b2db-16eb0dbe48b5"
    },
    {
      "id": "id72",
      "play_order": 72,
      "depth": 2,
      "title": "40 直播排名提升方法",
      "src": "text00071.html#A2fa64331-8f42-4e77-89ea-0207779d9fab",
      "file": "OEBPS/text00071.html",
      "fragment": "A2fa64331-8f42-4e77-89ea-0207779d9fab"
    },
    {
      "id": "id73",
      "play_order": 73,
      "depth": 2,
      "title": "41 淘品牌的打造（上）",
      "src": "text00072.html#A6d40639d-d286-4080-92d0-8c7064a30eb1",
      "file": "OEBPS/text00072.html",
      "fragment": "A6d40639d-d286-4080-92d0-8c7064a30eb1"
    },
    {
      "id": "id74",
      "play_order": 74,
      "depth": 2,
      "title": "42 淘品牌的打造（中）",
      "src": "text00073.html#A067ce61a-36b7-4d32-a077-4df5dea7a780",
      "file": "OEBPS/text00073.html",
      "fragment": "A067ce61a-36b7-4d32-a077-4df5dea7a780"
    },
    {
      "id": "id75",
      "play_order": 75,
      "depth": 2,
      "title": "43 淘品牌的打造（下）",
      "src": "text00074.html#A4965111d-3ed2-4d7a-b921-617e9c01ba00",
      "file": "OEBPS/text00074.html",
      "fragment": "A4965111d-3ed2-4d7a-b921-617e9c01ba00"
    },
    {
      "id": "id76",
      "play_order": 76,
      "depth": 2,
      "title": "44 你浪费了多少“包裹价值”（上）",
      "src": "text00075.html#Abc42b896-e46f-41db-95a7-ac92e543c33b",
      "file": "OEBPS/text00075.html",
      "fragment": "Abc42b896-e46f-41db-95a7-ac92e543c33b"
    },
    {
      "id": "id77",
      "play_order": 77,
      "depth": 2,
      "title": "45 你浪费了多少“包裹价值”（下）",
      "src": "text00076.html#A3d127be1-3065-4ce8-81ff-b037ec3c890d",
      "file": "OEBPS/text00076.html",
      "fragment": "A3d127be1-3065-4ce8-81ff-b037ec3c890d"
    },
    {
      "id": "id78",
      "play_order": 78,
      "depth": 2,
      "title": "46 店铺标签、商品标签和人群标签",
      "src": "text00077.html#A9f28eb74-3884-40f7-9553-9243f02c2fc1",
      "file": "OEBPS/text00077.html",
      "fragment": "A9f28eb74-3884-40f7-9553-9243f02c2fc1"
    },
    {
      "id": "id79",
      "play_order": 79,
      "depth": 2,
      "title": "47 淘宝店招聘",
      "src": "text00078.html#Aacc361ed-583d-440b-abe3-994b6c3cab3e",
      "file": "OEBPS/text00078.html",
      "fragment": "Aacc361ed-583d-440b-abe3-994b6c3cab3e"
    },
    {
      "id": "id80",
      "play_order": 80,
      "depth": 2,
      "title": "48 淘宝运营团队管理（上）",
      "src": "text00079.html#Ab6df2491-d43e-4148-94ff-f4213b1d9ec0",
      "file": "OEBPS/text00079.html",
      "fragment": "Ab6df2491-d43e-4148-94ff-f4213b1d9ec0"
    },
    {
      "id": "id81",
      "play_order": 81,
      "depth": 2,
      "title": "49 淘宝运营团队管理（下）",
      "src": "text00080.html#A13b4e46a-57d7-4115-87bc-7b26947e11cd",
      "file": "OEBPS/text00080.html",
      "fragment": "A13b4e46a-57d7-4115-87bc-7b26947e11cd"
    },
    {
      "id": "id82",
      "play_order": 82,
      "depth": 2,
      "title": "50 价格战（上）",
      "src": "text00081.html#A2130db8c-307a-4e7d-981c-bcfe9a178f86",
      "file": "OEBPS/text00081.html",
      "fragment": "A2130db8c-307a-4e7d-981c-bcfe9a178f86"
    },
    {
      "id": "id83",
      "play_order": 83,
      "depth": 2,
      "title": "51 价格战（下）",
      "src": "text00082.html#A974f06a0-21af-44aa-af3f-090769c4cf46",
      "file": "OEBPS/text00082.html",
      "fragment": "A974f06a0-21af-44aa-af3f-090769c4cf46"
    },
    {
      "id": "id84",
      "play_order": 84,
      "depth": 2,
      "title": "52 直通车辅助搜索",
      "src": "text00083.html#Ac6b7205f-99d1-47b1-9ec7-933e417c5252",
      "file": "OEBPS/text00083.html",
      "fragment": "Ac6b7205f-99d1-47b1-9ec7-933e417c5252"
    },
    {
      "id": "id85",
      "play_order": 85,
      "depth": 2,
      "title": "53 生意参谋的使用说明书（上）",
      "src": "text00084.html#A457fce5d-607a-4374-911a-e50c6e5972e0",
      "file": "OEBPS/text00084.html",
      "fragment": "A457fce5d-607a-4374-911a-e50c6e5972e0"
    },
    {
      "id": "id86",
      "play_order": 86,
      "depth": 2,
      "title": "54 生意参谋的使用说明书（下）",
      "src": "text00085.html#Af2602a26-b241-4698-a3f5-62f475f267d8",
      "file": "OEBPS/text00085.html",
      "fragment": "Af2602a26-b241-4698-a3f5-62f475f267d8"
    },
    {
      "id": "id87",
      "play_order": 87,
      "depth": 2,
      "title": "55 淘宝店的财务探讨",
      "src": "text00086.html#A306eb93c-6c27-41a3-a40f-24b949b0ce40",
      "file": "OEBPS/text00086.html",
      "fragment": "A306eb93c-6c27-41a3-a40f-24b949b0ce40"
    },
    {
      "id": "id88",
      "play_order": 88,
      "depth": 2,
      "title": "56 淘宝运营成功密码",
      "src": "text00087.html#Ad201cd19-7bdf-4dc0-a5eb-a7ad98803930",
      "file": "OEBPS/text00087.html",
      "fragment": "Ad201cd19-7bdf-4dc0-a5eb-a7ad98803930"
    }
  ],
  "html_files": [
    "OEBPS/text00000.html",
    "OEBPS/text00001.html",
    "OEBPS/text00002.html",
    "OEBPS/text00003.html",
    "OEBPS/text00004.html",
    "OEBPS/text00005.html",
    "OEBPS/text00006.html",
    "OEBPS/text00007.html",
    "OEBPS/text00008.html",
    "OEBPS/text00009.html",
    "OEBPS/text00010.html",
    "OEBPS/text00011.html",
    "OEBPS/text00012.html",
    "OEBPS/text00013.html",
    "OEBPS/text00014.html",
    "OEBPS/text00015.html",
    "OEBPS/text00016.html",
    "OEBPS/text00017.html",
    "OEBPS/text00018.html",
    "OEBPS/text00019.html",
    "OEBPS/text00020.html",
    "OEBPS/text00021.html",
    "OEBPS/text00022.html",
    "OEBPS/text00023.html",
    "OEBPS/text00024.html",
    "OEBPS/text00025.html",
    "OEBPS/text00026.html",
    "OEBPS/text00027.html",
    "OEBPS/text00028.html",
    "OEBPS/text00029.html",
    "OEBPS/text00030.html",
    "OEBPS/text00031.html",
    "OEBPS/text00032.html",
    "OEBPS/text00033.html",
    "OEBPS/text00034.html",
    "OEBPS/text00035.html",
    "OEBPS/text00036.html",
    "OEBPS/text00037.html",
    "OEBPS/text00038.html",
    "OEBPS/text00039.html",
    "OEBPS/text00040.html",
    "OEBPS/text00041.html",
    "OEBPS/text00042.html",
    "OEBPS/text00043.html",
    "OEBPS/text00044.html",
    "OEBPS/text00045.html",
    "OEBPS/text00046.html",
    "OEBPS/text00047.html",
    "OEBPS/text00048.html",
    "OEBPS/text00049.html",
    "OEBPS/text00050.html",
    "OEBPS/text00051.html",
    "OEBPS/text00052.html",
    "OEBPS/text00053.html",
    "OEBPS/text00054.html",
    "OEBPS/text00055.html",
    "OEBPS/text00056.html",
    "OEBPS/text00057.html",
    "OEBPS/text00058.html",
    "OEBPS/text00059.html",
    "OEBPS/text00060.html",
    "OEBPS/text00061.html",
    "OEBPS/text00062.html",
    "OEBPS/text00063.html",
    "OEBPS/text00064.html",
    "OEBPS/text00065.html",
    "OEBPS/text00066.html",
    "OEBPS/text00067.html",
    "OEBPS/text00068.html",
    "OEBPS/text00069.html",
    "OEBPS/text00070.html",
    "OEBPS/text00071.html",
    "OEBPS/text00072.html",
    "OEBPS/text00073.html",
    "OEBPS/text00074.html",
    "OEBPS/text00075.html",
    "OEBPS/text00076.html",
    "OEBPS/text00077.html",
    "OEBPS/text00078.html",
    "OEBPS/text00079.html",
    "OEBPS/text00080.html",
    "OEBPS/text00081.html",
    "OEBPS/text00082.html",
    "OEBPS/text00083.html",
    "OEBPS/text00084.html",
    "OEBPS/text00085.html",
    "OEBPS/text00086.html",
    "OEBPS/text00087.html"
  ],
  "image_files": [
    "OEBPS/Image00000.jpg",
    "OEBPS/Image00001.jpg",
    "OEBPS/Image00002.jpg",
    "OEBPS/Image00003.jpg",
    "OEBPS/Image00004.jpg",
    "OEBPS/Image00005.jpg",
    "OEBPS/Image00006.jpg",
    "OEBPS/Image00007.jpg",
    "OEBPS/Image00008.jpg",
    "OEBPS/Image00009.jpg",
    "OEBPS/Image00010.jpg",
    "OEBPS/Image00011.jpg",
    "OEBPS/Image00012.jpg",
    "OEBPS/Image00013.jpg",
    "OEBPS/Image00014.jpg",
    "OEBPS/Image00015.jpg",
    "OEBPS/Image00016.jpg",
    "OEBPS/Image00017.jpg",
    "OEBPS/Image00018.jpg",
    "OEBPS/Image00019.jpg",
    "OEBPS/Image00020.jpg",
    "OEBPS/Image00021.jpg",
    "OEBPS/Image00022.jpg",
    "OEBPS/Image00023.jpg",
    "OEBPS/Image00024.jpg",
    "OEBPS/Image00025.jpg",
    "OEBPS/Image00026.jpg",
    "OEBPS/Image00027.jpg",
    "OEBPS/Image00028.jpg",
    "OEBPS/Image00029.jpg",
    "OEBPS/Image00030.jpg",
    "OEBPS/Image00031.jpg",
    "OEBPS/Image00032.jpg",
    "OEBPS/Image00033.jpg",
    "OEBPS/Image00034.jpg",
    "OEBPS/Image00035.jpg",
    "OEBPS/Image00036.jpg",
    "OEBPS/Image00037.jpg",
    "OEBPS/Image00038.jpg",
    "OEBPS/Image00039.jpg",
    "OEBPS/Image00040.jpg",
    "OEBPS/Image00041.jpg",
    "OEBPS/Image00042.jpg",
    "OEBPS/Image00043.jpg",
    "OEBPS/Image00044.jpg",
    "OEBPS/Image00045.jpg",
    "OEBPS/Image00046.jpg",
    "OEBPS/Image00047.jpg",
    "OEBPS/Image00048.jpg",
    "OEBPS/Image00049.jpg",
    "OEBPS/Image00050.jpg",
    "OEBPS/Image00051.jpg",
    "OEBPS/Image00052.jpg",
    "OEBPS/Image00053.jpg",
    "OEBPS/Image00054.jpg",
    "OEBPS/Image00055.jpg",
    "OEBPS/Image00056.jpg",
    "OEBPS/Image00057.jpg",
    "OEBPS/Image00058.jpg",
    "OEBPS/Image00060.jpg"
  ],
  "warnings": []
}
